{"type":"UIControl","widthType":"RELATIVE","heightType":"RELATIVE","name":"Root","children":[{"type":"UIPanel","width":200,"xAnchor":1,"align":"TOP_RIGHT","heightType":"RELATIVE","children":[{"type":"UILabel","width":200,"height":20,"style":"panelTitle","textComponent":{"text":"Resources","font":{"align":"LEFT","padding":{}}}},{"type":"UIControl","y":52,"height":-52,"widthType":"RELATIVE","heightType":"RELATIVE","name":"inspectorTexture","children":[{"type":"UIControl","y":208,"width":200,"height":-208,"heightType":"RELATIVE","name":"pnlCmdStack","children":[{"type":"UICheckBox","height":50,"widthType":"RELATIVE","name":"chkCmdFILL","style":"selectBox","children":[{"type":"UILabel","width":23,"xAnchor":1,"align":"TOP_RIGHT","heightType":"RELATIVE","style":"panelTitle","clickThrough":true,"textComponent":{"text":"5","font":{"align":"LEFT","padding":{}}}},{"type":"UILabel","x":4,"width":122,"heightType":"RELATIVE","clickThrough":true,"textComponent":{"text":"FILL","font":{"align":"LEFT","padding":{}}}},{"type":"UIPanel","x":50,"width":40,"height":34,"xAnchor":0.5,"yAnchor":0.5,"align":"CENTER","name":"color","style":"colorPicker","color":"ff993eff"}],"textComponent":{"font":{"padding":{}}}},{"type":"UICheckBox","y":50,"height":50,"widthType":"RELATIVE","name":"chkCmdRECT","style":"selectBox","children":[{"type":"UILabel","width":23,"xAnchor":1,"align":"TOP_RIGHT","heightType":"RELATIVE","style":"panelTitle","clickThrough":true,"textComponent":{"text":"9","font":{"align":"LEFT","padding":{}}}},{"type":"UILabel","x":4,"width":122,"heightType":"RELATIVE","clickThrough":true,"textComponent":{"text":"RECT","font":{"align":"LEFT","padding":{}}}},{"type":"UIPanel","x":50,"width":40,"height":34,"xAnchor":0.5,"yAnchor":0.5,"align":"CENTER","name":"color","style":"colorPicker","color":"ff993eff"}],"textComponent":{"font":{"padding":{}}}},{"type":"UICheckBox","y":100,"height":50,"widthType":"RELATIVE","name":"chkCmdBEVEL","style":"selectBox","children":[{"type":"UILabel","width":23,"xAnchor":1,"align":"TOP_RIGHT","heightType":"RELATIVE","style":"panelTitle","clickThrough":true,"textComponent":{"text":"10","font":{"align":"LEFT","padding":{}}}},{"type":"UILabel","x":4,"width":44,"heightType":"RELATIVE","clickThrough":true,"textComponent":{"text":"BEVEL","font":{"align":"LEFT","padding":{}}}},{"type":"UIPanel","x":50,"width":40,"height":34,"xAnchor":0.5,"yAnchor":0.5,"align":"CENTER","name":"color","style":"colorPicker","color":"ff993eff"},{"type":"UITextBox","x":90,"y":22,"width":36,"height":24,"name":"txtBevel","textComponent":{"text":"3","font":{"padding":{}}},"numerical":true},{"type":"UILabel","x":90,"y":2,"width":36,"height":20,"textComponent":{"text":"Bevel","font":{"align":"LEFT","padding":{}}}}],"textComponent":{"font":{"padding":{}}}},{"type":"UICheckBox","y":150,"height":50,"widthType":"RELATIVE","name":"chkCmdCIRCLE","style":"selectBox","children":[{"type":"UILabel","width":23,"xAnchor":1,"align":"TOP_RIGHT","heightType":"RELATIVE","style":"panelTitle","clickThrough":true,"textComponent":{"text":"8","font":{"align":"LEFT","padding":{}}}},{"type":"UILabel","x":4,"width":44,"heightType":"RELATIVE","clickThrough":true,"textComponent":{"text":"CIRCLE","font":{"align":"LEFT","padding":{}}}},{"type":"UIPanel","x":50,"width":40,"height":34,"xAnchor":0.5,"yAnchor":0.5,"align":"CENTER","name":"color","style":"colorPicker","color":"ff993eff"},{"type":"UITextBox","x":90,"y":22,"width":36,"height":24,"name":"txtRadius","textComponent":{"text":"20","font":{"padding":{}}},"numerical":true},{"type":"UILabel","x":90,"y":2,"width":36,"height":20,"textComponent":{"text":"Radius","font":{"align":"LEFT","padding":{}}}}],"textComponent":{"font":{"padding":{}}}},{"type":"UICheckBox","y":200,"height":50,"widthType":"RELATIVE","name":"chkCmdBEVEL_CIRCLE","style":"selectBox","children":[{"type":"UILabel","width":23,"xAnchor":1,"align":"TOP_RIGHT","heightType":"RELATIVE","style":"panelTitle","clickThrough":true,"textComponent":{"text":"9","font":{"align":"LEFT","padding":{}}}},{"type":"UILabel","x":4,"width":44,"height":25,"clickThrough":true,"textComponent":{"text":"BEVEL","font":{"align":"LEFT","padding":{}}}},{"type":"UIPanel","x":50,"width":40,"height":34,"xAnchor":0.5,"yAnchor":0.5,"align":"CENTER","name":"color","style":"colorPicker","color":"ff993eff"},{"type":"UITextBox","x":90,"y":22,"width":36,"height":24,"name":"txtBevel","textComponent":{"text":"3","font":{"padding":{}}},"numerical":true},{"type":"UILabel","x":90,"y":2,"width":36,"height":20,"clickThrough":true,"textComponent":{"text":"Bevel","font":{"align":"LEFT","padding":{}}}},{"type":"UILabel","x":4,"y":25,"width":44,"height":25,"clickThrough":true,"textComponent":{"text":"CIRCLE","font":{"align":"LEFT","padding":{}}}},{"type":"UITextBox","x":52,"y":22,"width":36,"height":24,"name":"txtRadius","textComponent":{"text":"20","font":{"padding":{}}},"numerical":true},{"type":"UILabel","x":52,"y":2,"width":36,"height":20,"clickThrough":true,"textComponent":{"text":"Radius","font":{"align":"LEFT","padding":{}}}}],"textComponent":{"font":{"padding":{}}}},{"type":"UICheckBox","y":250,"height":50,"widthType":"RELATIVE","name":"chkCmdLINE","style":"selectBox","children":[{"type":"UILabel","width":23,"xAnchor":1,"align":"TOP_RIGHT","heightType":"RELATIVE","style":"panelTitle","clickThrough":true,"textComponent":{"text":"10","font":{"align":"LEFT","padding":{}}}},{"type":"UILabel","x":4,"width":44,"heightType":"RELATIVE","clickThrough":true,"textComponent":{"text":"LINE","font":{"align":"LEFT","padding":{}}}},{"type":"UIPanel","x":50,"width":40,"height":34,"xAnchor":0.5,"yAnchor":0.5,"align":"CENTER","name":"color","style":"colorPicker","color":"ff993eff"},{"type":"UITextBox","x":90,"y":22,"width":36,"height":24,"name":"txtSize","textComponent":{"text":"3","font":{"padding":{}}},"numerical":true},{"type":"UILabel","x":90,"y":2,"width":36,"height":20,"clickThrough":true,"textComponent":{"text":"Size","font":{"align":"LEFT","padding":{}}}}],"textComponent":{"font":{"padding":{}}}},{"type":"UICheckBox","y":300,"height":50,"widthType":"RELATIVE","name":"chkCmdNORMAL_MAP","style":"selectBox","children":[{"type":"UILabel","width":23,"xAnchor":1,"align":"TOP_RIGHT","heightType":"RELATIVE","style":"panelTitle","clickThrough":true,"textComponent":{"text":"1","font":{"align":"LEFT","padding":{}}}},{"type":"UILabel","x":4,"width":169,"heightType":"RELATIVE","clickThrough":true,"textComponent":{"text":"NORMAL MAP","font":{"align":"LEFT","padding":{}}}}],"textComponent":{"font":{"padding":{}}}},{"type":"UICheckBox","y":350,"height":50,"widthType":"RELATIVE","name":"chkCmdGRADIENT","style":"selectBox","children":[{"type":"UILabel","width":23,"xAnchor":1,"align":"TOP_RIGHT","heightType":"RELATIVE","style":"panelTitle","clickThrough":true,"textComponent":{"text":"10","font":{"align":"LEFT","padding":{}}}},{"type":"UILabel","x":4,"width":78,"height":25,"clickThrough":true,"textComponent":{"text":"GRADIENT","font":{"align":"LEFT","padding":{}}}},{"type":"UIPanel","x":50,"width":40,"height":34,"xAnchor":0.5,"yAnchor":0.5,"align":"CENTER","name":"colorTo","style":"colorPicker","color":"000000ff"},{"type":"UIPanel","x":6,"width":40,"height":34,"xAnchor":0.5,"yAnchor":0.5,"align":"CENTER","name":"colorFrom","style":"colorPicker"},{"type":"UICheckBox","x":4,"y":25,"width":60,"height":25,"textComponent":{"text":"Vertical","font":{"padding":{}}}}],"textComponent":{"font":{"padding":{}}}}]},{"type":"UILabel","y":188,"width":200,"height":20,"style":"panelTitle","textComponent":{"text":"Command Stack","font":{"align":"LEFT","padding":{}}}},{"type":"UITextBox","x":20,"y":24,"width":64,"height":24,"name":"txtImgW","textComponent":{"text":"0","font":{"padding":{}}},"numerical":true},{"type":"UITextBox","x":104,"y":24,"width":64,"height":24,"name":"txtImgH","textComponent":{"text":"0","font":{"padding":{}}},"numerical":true},{"type":"UILabel","x":4,"y":24,"width":12,"height":24,"textComponent":{"text":"W","font":{"align":"LEFT","padding":{}}}},{"type":"UILabel","x":92,"y":24,"width":8,"height":24,"textComponent":{"text":"H","font":{"align":"LEFT","padding":{}}}},{"type":"UILabel","width":200,"height":20,"style":"panelTitle","textComponent":{"text":"Texture","font":{"align":"LEFT","padding":{}}}},{"type":"UILabel","y":52,"width":200,"height":20,"style":"panelTitle","textComponent":{"text":"Commands","font":{"align":"LEFT","padding":{}}}},{"type":"UIButton","x":0.18,"y":76,"width":0.3,"height":24,"xAnchor":0.5,"xType":"PERCENTAGE","widthType":"PERCENTAGE","name":"btnCmdFILL","textComponent":{"text":"FILL","font":{"align":"CENTER","padding":{}}}},{"type":"UIButton","x":0.5,"y":76,"width":0.3,"height":24,"xAnchor":0.5,"xType":"PERCENTAGE","widthType":"PERCENTAGE","name":"btnCmdRECT","textComponent":{"text":"RECT","font":{"align":"CENTER","padding":{}}}},{"type":"UIButton","x":0.82,"y":76,"width":0.3,"height":24,"xAnchor":0.5,"xType":"PERCENTAGE","widthType":"PERCENTAGE","name":"btnCmdBEVEL","textComponent":{"text":"BEVEL","font":{"align":"CENTER","padding":{}}}},{"type":"UIButton","x":0.18,"y":104,"width":0.3,"height":24,"xAnchor":0.5,"xType":"PERCENTAGE","widthType":"PERCENTAGE","name":"btnCmdCIRCLE","textComponent":{"text":"CIRCLE","font":{"align":"CENTER","padding":{}}}},{"type":"UIButton","x":0.66,"y":104,"width":0.62,"height":24,"xAnchor":0.5,"xType":"PERCENTAGE","widthType":"PERCENTAGE","name":"btnCmdBEVEL_CIRCLE","textComponent":{"text":"BEVEL CIRCLE","font":{"align":"CENTER","padding":{}}}},{"type":"UIButton","x":0.18,"y":132,"width":0.3,"height":24,"xAnchor":0.5,"xType":"PERCENTAGE","widthType":"PERCENTAGE","name":"btnCmdLINE","textComponent":{"text":"LINE","font":{"align":"CENTER","padding":{}}}},{"type":"UIButton","x":0.66,"y":132,"width":0.62,"height":24,"xAnchor":0.5,"xType":"PERCENTAGE","widthType":"PERCENTAGE","name":"btnCmdNORMAL_MAP","textComponent":{"text":"NORMAL MAP","font":{"align":"CENTER","padding":{}}}},{"type":"UIButton","x":0.18,"y":160,"width":0.3,"height":24,"xAnchor":0.5,"xType":"PERCENTAGE","widthType":"PERCENTAGE","name":"btnCmdGRADIENT","textComponent":{"text":"GRADIENT","font":{"align":"CENTER","padding":{}}}}]},{"type":"UIButton","x":0.18,"y":24,"width":0.3,"height":24,"xAnchor":0.5,"xType":"PERCENTAGE","widthType":"PERCENTAGE","name":"btnTextures","textComponent":{"text":"Textures","font":{"align":"CENTER","padding":{}}}},{"type":"UIButton","x":0.5,"y":24,"width":0.3,"height":24,"xAnchor":0.5,"xType":"PERCENTAGE","widthType":"PERCENTAGE","name":"btnMeshes","textComponent":{"text":"Meshes","font":{"align":"CENTER","padding":{}}}},{"type":"UIButton","x":0.82,"y":24,"width":0.3,"height":24,"xAnchor":0.5,"xType":"PERCENTAGE","widthType":"PERCENTAGE","name":"btnScene","textComponent":{"text":"Scene","font":{"align":"CENTER","padding":{}}}},{"type":"UIControl","y":52,"height":-52,"widthType":"RELATIVE","heightType":"RELATIVE","name":"inspectorTextures","visible":false,"children":[{"type":"UILabel","width":200,"height":20,"style":"panelTitle","textComponent":{"text":"Textures","font":{"align":"LEFT","padding":{}}}},{"type":"UIButton","x":4,"y":24,"width":-8,"height":24,"widthType":"RELATIVE","name":"btnNewTexture","textComponent":{"text":"New","font":{"align":"CENTER","padding":{}}}},{"type":"UIButton","x":4,"y":52,"width":-8,"height":24,"widthType":"RELATIVE","name":"btnEditTexture","textComponent":{"text":"Edit Selected","font":{"align":"CENTER","padding":{}}}},{"type":"UIButton","x":4,"y":80,"width":-8,"height":24,"widthType":"RELATIVE","name":"btnDeleteTexture","textComponent":{"text":"Delete Selected","font":{"align":"CENTER","padding":{}}}}]}]},{"type":"UIControl","width":-200,"widthType":"RELATIVE","heightType":"RELATIVE","name":"viewTextures","visible":false},{"type":"UIControl","width":-200,"widthType":"RELATIVE","heightType":"RELATIVE","name":"viewTexture","visible":false,"children":[{"type":"UIPanel","width":256,"height":256,"xAnchor":0.5,"yAnchor":0.5,"align":"CENTER","name":"pnlTexture"}]}]}